tooluser-0.2.4.dist-info/METADATA
tooluser-0.2.4.dist-info/WHEEL
tooluser-0.2.4.dist-info/entry_points.txt
tooluser-0.2.4.dist-info/licenses/LICENSE
tooluser/__init__.py
tooluser/hermes_transform.py
tooluser/tool_user.py
tooluser/transform.py
tooluser-0.2.4.dist-info/RECORD
