Metadata-Version: 2.1
Name: tooluser
Version: 0.2.4
Summary: Enable tool-use ability for any LLM model (DeepSeek V3/R1, etc.)
Author-Email: yanli <mail@yanli.one>
License: MIT
Requires-Python: >=3.10
Requires-Dist: openai>=1.75.0
Requires-Dist: jinja2>=3.1.6
Requires-Dist: json-repair>=0.41.1
